LICENSE
MANIFEST.in
README.rst
setup.cfg
setup.py
itsy/__init__.py
itsy/client.py
itsy/document.py
itsy/parsers.py
itsy/queue.py
itsy/utils.py
itsy.egg-info/PKG-INFO
itsy.egg-info/SOURCES.txt
itsy.egg-info/dependency_links.txt
itsy.egg-info/not-zip-safe
itsy.egg-info/requires.txt
itsy.egg-info/top_level.txt