Metadata-Version: 1.1
Name: itsy
Version: 0.1
Summary: Web crawling and scraping framework
Home-page: http://github.com/storborg/itsy
Author: Scott Torborg
Author-email: storborg@gmail.com
License: MIT
Platform: UNKNOWN
Classifier: License :: OSI Approved :: MIT License
Classifier: Programming Language :: Python :: 2
Classifier: Programming Language :: Python :: 2.7
